.long-description.html
README.rst
setup.py
src/collective/__init__.py
src/collective.behavior.stock.egg-info/PKG-INFO
src/collective.behavior.stock.egg-info/SOURCES.txt
src/collective.behavior.stock.egg-info/dependency_links.txt
src/collective.behavior.stock.egg-info/entry_points.txt
src/collective.behavior.stock.egg-info/namespace_packages.txt
src/collective.behavior.stock.egg-info/not-zip-safe
src/collective.behavior.stock.egg-info/requires.txt
src/collective.behavior.stock.egg-info/top_level.txt
src/collective/behavior/__init__.py
src/collective/behavior/stock/__init__.py
src/collective/behavior/stock/behavior.py
src/collective/behavior/stock/configure.zcml
src/collective/behavior/stock/interfaces.py
src/collective/behavior/stock/schema.py
src/collective/behavior/stock/docs/CONTRIBUTORS.rst
src/collective/behavior/stock/docs/CREDITS.rst
src/collective/behavior/stock/docs/HISTORY.rst
src/collective/behavior/stock/docs/INSTALL.rst
src/collective/behavior/stock/docs/LICENSE.rst
src/collective/behavior/stock/locales/collective.behavior.stock.pot
src/collective/behavior/stock/locales/fi/LC_MESSAGES/collective.behavior.stock.po
src/collective/behavior/stock/profiles/default/catalog.xml
src/collective/behavior/stock/profiles/default/metadata.xml
src/collective/behavior/stock/tests/__init__.py
src/collective/behavior/stock/tests/base.py
src/collective/behavior/stock/tests/test_IStock.py
src/collective/behavior/stock/tests/test_Stock.py
src/collective/behavior/stock/tests/test_setup.py
src/collective/behavior/stock/tests/dexterity/__init__.py
src/collective/behavior/stock/tests/dexterity/configure.zcml
src/collective/behavior/stock/tests/dexterity/folder.py
src/collective/behavior/stock/tests/dexterity/profiles/default/types.xml
src/collective/behavior/stock/tests/dexterity/profiles/default/types/collective.behavior.stock.Folder.xml