Metadata-Version: 1.1
Name: collective.behavior.stock
Version: 0.6
Summary: Provides stock related behavior to dexterity content types.
Home-page: https://github.com/collective/collective.behavior.stock/
Author: Taito Horiuchi
Author-email: taito.horiuchi@gmail.com
License: BSD
Platform: UNKNOWN
Classifier: Framework :: Plone
Classifier: Framework :: Plone :: 4.3
Classifier: License :: OSI Approved :: BSD License
Classifier: Programming Language :: Python
Classifier: Programming Language :: Python :: 2.7
